eeisp/LouvainSigned.py
eeisp/__init__.py
eeisp/network.py
eeisp-0.6.0.data/scripts/eeisp
eeisp-0.6.0.data/scripts/eeisp.Louvain
eeisp-0.6.0.data/scripts/eeisp.LouvainSigned
eeisp-0.6.0.data/scripts/eeisp.heatmap
eeisp-0.6.0.data/scripts/eeisp_add_genename_from_geneid
eeisp-0.6.0.dist-info/LICENSE
eeisp-0.6.0.dist-info/METADATA
eeisp-0.6.0.dist-info/WHEEL
eeisp-0.6.0.dist-info/top_level.txt
eeisp-0.6.0.dist-info/RECORD
