Metadata-Version: 2.1
Name: eeisp
Version: 0.6.0
Summary: Identify gene pairs that are codependent and mutually exclusive from single-cell RNA-seq data.
Home-page: https://github.com/nakatolab/EEISP
Author: Ryuichiro Nakato
Author-email: rnakato@iqb.u-tokyo.ac.jp
License: GPL3.0
Keywords: eeisp scRNA-seq
Classifier: Programming Language :: Python :: 3
Classifier: Operating System :: OS Independent
Requires-Python: >=3.6
License-File: LICENSE
Requires-Dist: numpy >=1.14.2
Requires-Dist: pandas >=0.22.0
Requires-Dist: scipy >=1.3
Requires-Dist: matplotlib
Requires-Dist: seaborn
Requires-Dist: networkx
Requires-Dist: igraph
